<mes:StructureSpecificData xmlns:com="http://www.sdmx.org/resources/sdmxml/schemas/v2_1/common" xmlns:data="http://www.sdmx.org/resources/sdmxml/schemas/v2_1/data/structurespecific" xmlns:str="http://www.sdmx.org/resources/sdmxml/schemas/v2_1/structure" xmlns:mes="http://www.sdmx.org/resources/sdmxml/schemas/v2_1/message" xmlns:gen="http://www.sdmx.org/resources/sdmxml/schemas/v2_1/data/generic" xmlns:footer="http://www.sdmx.org/resources/sdmxml/schemas/v2_1/message/footer" xmlns:xsi="http://www.w3.org/2001/XMLSchema-instance"><mes:Header><mes:ID>IREF1617897066</mes:ID><mes:Test>true</mes:Test><mes:Prepared>2021-04-08T15:51:06</mes:Prepared><mes:Sender id="open-sdg_sdg-build@130"/><mes:Structure structureID="SDG" dimensionAtObservation="TIME_PERIOD"><com:Structure><URN>urn:sdmx:org.sdmx.infomodel.datastructure.DataStructure=IAEG-SDGs:SDG(1.4)</URN></com:Structure></mes:Structure></mes:Header><mes:DataSet structureRef="SDG"><Series FREQ="A" REPORTING_TYPE="N" SERIES="&#1082; &#1086;&#1088;&#1075;&#1072;&#1085;&#1072;&#1084; &#1087;&#1088;&#1086;&#1082;&#1091;&#1088;&#1072;&#1090;&#1091;&#1088;&#1099;" REF_AREA="_T" SEX="_T" AGE="_T" URBANISATION="_T" INCOME_WEALTH_QUANTILE="_T" EDUCATION_LEV="_T" OCCUPATION="_T" CUST_BREAKDOWN="_T" COMPOSITE_BREAKDOWN="_L_TRST_HIGH" DISABILITY_STATUS="_T" ACTIVITY="_T" PRODUCT="_T" UNIT_MEASURE="PT"><Obs TIME_DETAIL="2016" OBS_VALUE="38.7" TIME_PERIOD="2016"/></Series><Series FREQ="A" REPORTING_TYPE="N" SERIES="&#1082; &#1086;&#1088;&#1075;&#1072;&#1085;&#1072;&#1084; &#1087;&#1088;&#1086;&#1082;&#1091;&#1088;&#1072;&#1090;&#1091;&#1088;&#1099;" REF_AREA="_T" SEX="_T" AGE="_T" URBANISATION="_T" INCOME_WEALTH_QUANTILE="_T" EDUCATION_LEV="_T" OCCUPATION="_T" CUST_BREAKDOWN="_T" COMPOSITE_BREAKDOWN="_L_TRST_AVG" DISABILITY_STATUS="_T" ACTIVITY="_T" PRODUCT="_T" UNIT_MEASURE="PT"><Obs TIME_DETAIL="2016" OBS_VALUE="43.3" TIME_PERIOD="2016"/></Series><Series FREQ="A" REPORTING_TYPE="N" SERIES="&#1082; &#1086;&#1088;&#1075;&#1072;&#1085;&#1072;&#1084; &#1087;&#1088;&#1086;&#1082;&#1091;&#1088;&#1072;&#1090;&#1091;&#1088;&#1099;" REF_AREA="_T" SEX="_T" AGE="_T" URBANISATION="_T" INCOME_WEALTH_QUANTILE="_T" EDUCATION_LEV="_T" OCCUPATION="_T" CUST_BREAKDOWN="_T" COMPOSITE_BREAKDOWN="_L_TRST_LOW" DISABILITY_STATUS="_T" ACTIVITY="_T" PRODUCT="_T" UNIT_MEASURE="PT"><Obs TIME_DETAIL="2016" OBS_VALUE="4.1" TIME_PERIOD="2016"/></Series><Series FREQ="A" REPORTING_TYPE="N" SERIES="&#1082; &#1086;&#1088;&#1075;&#1072;&#1085;&#1072;&#1084; &#1087;&#1088;&#1086;&#1082;&#1091;&#1088;&#1072;&#1090;&#1091;&#1088;&#1099;" REF_AREA="_T" SEX="_T" AGE="_T" URBANISATION="_T" INCOME_WEALTH_QUANTILE="_T" EDUCATION_LEV="_T" OCCUPATION="_T" CUST_BREAKDOWN="_T" COMPOSITE_BREAKDOWN="_L_TRST_NO" DISABILITY_STATUS="_T" ACTIVITY="_T" PRODUCT="_T" UNIT_MEASURE="PT"><Obs TIME_DETAIL="2016" OBS_VALUE="2.0" TIME_PERIOD="2016"/></Series><Series FREQ="A" REPORTING_TYPE="N" SERIES="&#1082; &#1086;&#1088;&#1075;&#1072;&#1085;&#1072;&#1084; &#1087;&#1088;&#1086;&#1082;&#1091;&#1088;&#1072;&#1090;&#1091;&#1088;&#1099;" REF_AREA="_T" SEX="_T" AGE="_T" URBANISATION="_T" INCOME_WEALTH_QUANTILE="_T" EDUCATION_LEV="_T" OCCUPATION="_T" CUST_BREAKDOWN="_T" COMPOSITE_BREAKDOWN="_L_TRST_NEV" DISABILITY_STATUS="_T" ACTIVITY="_T" PRODUCT="_T" UNIT_MEASURE="PT"><Obs TIME_DETAIL="2016" OBS_VALUE="11.8" TIME_PERIOD="2016"/></Series><Series FREQ="A" REPORTING_TYPE="N" SERIES="&#1082; &#1086;&#1088;&#1075;&#1072;&#1085;&#1072;&#1084; &#1074;&#1085;&#1091;&#1090;&#1088;&#1077;&#1085;&#1085;&#1080;&#1093; &#1076;&#1077;&#1083;" REF_AREA="_T" SEX="_T" AGE="_T" URBANISATION="_T" INCOME_WEALTH_QUANTILE="_T" EDUCATION_LEV="_T" OCCUPATION="_T" CUST_BREAKDOWN="_T" COMPOSITE_BREAKDOWN="_L_TRST_HIGH" DISABILITY_STATUS="_T" ACTIVITY="_T" PRODUCT="_T" UNIT_MEASURE="PT"><Obs TIME_DETAIL="2016" OBS_VALUE="29.8" TIME_PERIOD="2016"/></Series><Series FREQ="A" REPORTING_TYPE="N" SERIES="&#1082; &#1086;&#1088;&#1075;&#1072;&#1085;&#1072;&#1084; &#1074;&#1085;&#1091;&#1090;&#1088;&#1077;&#1085;&#1085;&#1080;&#1093; &#1076;&#1077;&#1083;" REF_AREA="_T" SEX="_T" AGE="_T" URBANISATION="_T" INCOME_WEALTH_QUANTILE="_T" EDUCATION_LEV="_T" OCCUPATION="_T" CUST_BREAKDOWN="_T" COMPOSITE_BREAKDOWN="_L_TRST_AVG" DISABILITY_STATUS="_T" ACTIVITY="_T" PRODUCT="_T" UNIT_MEASURE="PT"><Obs TIME_DETAIL="2016" OBS_VALUE="51.6" TIME_PERIOD="2016"/></Series><Series FREQ="A" REPORTING_TYPE="N" SERIES="&#1082; &#1086;&#1088;&#1075;&#1072;&#1085;&#1072;&#1084; &#1074;&#1085;&#1091;&#1090;&#1088;&#1077;&#1085;&#1085;&#1080;&#1093; &#1076;&#1077;&#1083;" REF_AREA="_T" SEX="_T" AGE="_T" URBANISATION="_T" INCOME_WEALTH_QUANTILE="_T" EDUCATION_LEV="_T" OCCUPATION="_T" CUST_BREAKDOWN="_T" COMPOSITE_BREAKDOWN="_L_TRST_LOW" DISABILITY_STATUS="_T" ACTIVITY="_T" PRODUCT="_T" UNIT_MEASURE="PT"><Obs TIME_DETAIL="2016" OBS_VALUE="6.6" TIME_PERIOD="2016"/></Series><Series FREQ="A" REPORTING_TYPE="N" SERIES="&#1082; &#1086;&#1088;&#1075;&#1072;&#1085;&#1072;&#1084; &#1074;&#1085;&#1091;&#1090;&#1088;&#1077;&#1085;&#1085;&#1080;&#1093; &#1076;&#1077;&#1083;" REF_AREA="_T" SEX="_T" AGE="_T" URBANISATION="_T" INCOME_WEALTH_QUANTILE="_T" EDUCATION_LEV="_T" OCCUPATION="_T" CUST_BREAKDOWN="_T" COMPOSITE_BREAKDOWN="_L_TRST_NO" DISABILITY_STATUS="_T" ACTIVITY="_T" PRODUCT="_T" UNIT_MEASURE="PT"><Obs TIME_DETAIL="2016" OBS_VALUE="3.5" TIME_PERIOD="2016"/></Series><Series FREQ="A" REPORTING_TYPE="N" SERIES="&#1082; &#1086;&#1088;&#1075;&#1072;&#1085;&#1072;&#1084; &#1074;&#1085;&#1091;&#1090;&#1088;&#1077;&#1085;&#1085;&#1080;&#1093; &#1076;&#1077;&#1083;" REF_AREA="_T" SEX="_T" AGE="_T" URBANISATION="_T" INCOME_WEALTH_QUANTILE="_T" EDUCATION_LEV="_T" OCCUPATION="_T" CUST_BREAKDOWN="_T" COMPOSITE_BREAKDOWN="_L_TRST_NEV" DISABILITY_STATUS="_T" ACTIVITY="_T" PRODUCT="_T" UNIT_MEASURE="PT"><Obs TIME_DETAIL="2016" OBS_VALUE="8.7" TIME_PERIOD="2016"/></Series><Series FREQ="A" REPORTING_TYPE="N" SERIES="&#1082; &#1072;&#1085;&#1090;&#1080;&#1082;&#1086;&#1088;&#1088;&#1091;&#1087;&#1094;&#1094;&#1080;&#1086;&#1085;&#1085;&#1086;&#1081; &#1089;&#1083;&#1091;&#1078;&#1073;&#1077;" REF_AREA="_T" SEX="_T" AGE="_T" URBANISATION="_T" INCOME_WEALTH_QUANTILE="_T" EDUCATION_LEV="_T" OCCUPATION="_T" CUST_BREAKDOWN="_T" COMPOSITE_BREAKDOWN="_L_TRST_HIGH" DISABILITY_STATUS="_T" ACTIVITY="_T" PRODUCT="_T" UNIT_MEASURE="PT"><Obs TIME_DETAIL="2016" OBS_VALUE="16.1" TIME_PERIOD="2016"/></Series><Series FREQ="A" REPORTING_TYPE="N" SERIES="&#1082; &#1072;&#1085;&#1090;&#1080;&#1082;&#1086;&#1088;&#1088;&#1091;&#1087;&#1094;&#1094;&#1080;&#1086;&#1085;&#1085;&#1086;&#1081; &#1089;&#1083;&#1091;&#1078;&#1073;&#1077;" REF_AREA="_T" SEX="_T" AGE="_T" URBANISATION="_T" INCOME_WEALTH_QUANTILE="_T" EDUCATION_LEV="_T" OCCUPATION="_T" CUST_BREAKDOWN="_T" COMPOSITE_BREAKDOWN="_L_TRST_AVG" DISABILITY_STATUS="_T" ACTIVITY="_T" PRODUCT="_T" UNIT_MEASURE="PT"><Obs TIME_DETAIL="2016" OBS_VALUE="38.6" TIME_PERIOD="2016"/></Series><Series FREQ="A" REPORTING_TYPE="N" SERIES="&#1082; &#1072;&#1085;&#1090;&#1080;&#1082;&#1086;&#1088;&#1088;&#1091;&#1087;&#1094;&#1094;&#1080;&#1086;&#1085;&#1085;&#1086;&#1081; &#1089;&#1083;&#1091;&#1078;&#1073;&#1077;" REF_AREA="_T" SEX="_T" AGE="_T" URBANISATION="_T" INCOME_WEALTH_QUANTILE="_T" EDUCATION_LEV="_T" OCCUPATION="_T" CUST_BREAKDOWN="_T" COMPOSITE_BREAKDOWN="_L_TRST_LOW" DISABILITY_STATUS="_T" ACTIVITY="_T" PRODUCT="_T" UNIT_MEASURE="PT"><Obs TIME_DETAIL="2016" OBS_VALUE="6.0" TIME_PERIOD="2016"/></Series><Series FREQ="A" REPORTING_TYPE="N" SERIES="&#1082; &#1072;&#1085;&#1090;&#1080;&#1082;&#1086;&#1088;&#1088;&#1091;&#1087;&#1094;&#1094;&#1080;&#1086;&#1085;&#1085;&#1086;&#1081; &#1089;&#1083;&#1091;&#1078;&#1073;&#1077;" REF_AREA="_T" SEX="_T" AGE="_T" URBANISATION="_T" INCOME_WEALTH_QUANTILE="_T" EDUCATION_LEV="_T" OCCUPATION="_T" CUST_BREAKDOWN="_T" COMPOSITE_BREAKDOWN="_L_TRST_NO" DISABILITY_STATUS="_T" ACTIVITY="_T" PRODUCT="_T" UNIT_MEASURE="PT"><Obs TIME_DETAIL="2016" OBS_VALUE="4.1" TIME_PERIOD="2016"/></Series><Series FREQ="A" REPORTING_TYPE="N" SERIES="&#1082; &#1072;&#1085;&#1090;&#1080;&#1082;&#1086;&#1088;&#1088;&#1091;&#1087;&#1094;&#1094;&#1080;&#1086;&#1085;&#1085;&#1086;&#1081; &#1089;&#1083;&#1091;&#1078;&#1073;&#1077;" REF_AREA="_T" SEX="_T" AGE="_T" URBANISATION="_T" INCOME_WEALTH_QUANTILE="_T" EDUCATION_LEV="_T" OCCUPATION="_T" CUST_BREAKDOWN="_T" COMPOSITE_BREAKDOWN="_L_TRST_NEV" DISABILITY_STATUS="_T" ACTIVITY="_T" PRODUCT="_T" UNIT_MEASURE="PT"><Obs TIME_DETAIL="2016" OBS_VALUE="35.1" TIME_PERIOD="2016"/></Series><Series FREQ="A" REPORTING_TYPE="N" SERIES="&#1082; &#1089;&#1083;&#1091;&#1078;&#1073;&#1077; &#1101;&#1082;&#1086;&#1085;&#1086;&#1084;&#1080;&#1095;&#1077;&#1089;&#1082;&#1080;&#1093; &#1088;&#1072;&#1089;&#1089;&#1083;&#1077;&#1076;&#1086;&#1074;&#1072;&#1085;&#1080;&#1081;" REF_AREA="_T" SEX="_T" AGE="_T" URBANISATION="_T" INCOME_WEALTH_QUANTILE="_T" EDUCATION_LEV="_T" OCCUPATION="_T" CUST_BREAKDOWN="_T" COMPOSITE_BREAKDOWN="_L_TRST_HIGH" DISABILITY_STATUS="_T" ACTIVITY="_T" PRODUCT="_T" UNIT_MEASURE="PT"><Obs TIME_DETAIL="2016" OBS_VALUE="14.3" TIME_PERIOD="2016"/></Series><Series FREQ="A" REPORTING_TYPE="N" SERIES="&#1082; &#1089;&#1083;&#1091;&#1078;&#1073;&#1077; &#1101;&#1082;&#1086;&#1085;&#1086;&#1084;&#1080;&#1095;&#1077;&#1089;&#1082;&#1080;&#1093; &#1088;&#1072;&#1089;&#1089;&#1083;&#1077;&#1076;&#1086;&#1074;&#1072;&#1085;&#1080;&#1081;" REF_AREA="_T" SEX="_T" AGE="_T" URBANISATION="_T" INCOME_WEALTH_QUANTILE="_T" EDUCATION_LEV="_T" OCCUPATION="_T" CUST_BREAKDOWN="_T" COMPOSITE_BREAKDOWN="_L_TRST_AVG" DISABILITY_STATUS="_T" ACTIVITY="_T" PRODUCT="_T" UNIT_MEASURE="PT"><Obs TIME_DETAIL="2016" OBS_VALUE="37.4" TIME_PERIOD="2016"/></Series><Series FREQ="A" REPORTING_TYPE="N" SERIES="&#1082; &#1089;&#1083;&#1091;&#1078;&#1073;&#1077; &#1101;&#1082;&#1086;&#1085;&#1086;&#1084;&#1080;&#1095;&#1077;&#1089;&#1082;&#1080;&#1093; &#1088;&#1072;&#1089;&#1089;&#1083;&#1077;&#1076;&#1086;&#1074;&#1072;&#1085;&#1080;&#1081;" REF_AREA="_T" SEX="_T" AGE="_T" URBANISATION="_T" INCOME_WEALTH_QUANTILE="_T" EDUCATION_LEV="_T" OCCUPATION="_T" CUST_BREAKDOWN="_T" COMPOSITE_BREAKDOWN="_L_TRST_LOW" DISABILITY_STATUS="_T" ACTIVITY="_T" PRODUCT="_T" UNIT_MEASURE="PT"><Obs TIME_DETAIL="2016" OBS_VALUE="5.4" TIME_PERIOD="2016"/></Series><Series FREQ="A" REPORTING_TYPE="N" SERIES="&#1082; &#1089;&#1083;&#1091;&#1078;&#1073;&#1077; &#1101;&#1082;&#1086;&#1085;&#1086;&#1084;&#1080;&#1095;&#1077;&#1089;&#1082;&#1080;&#1093; &#1088;&#1072;&#1089;&#1089;&#1083;&#1077;&#1076;&#1086;&#1074;&#1072;&#1085;&#1080;&#1081;" REF_AREA="_T" SEX="_T" AGE="_T" URBANISATION="_T" INCOME_WEALTH_QUANTILE="_T" EDUCATION_LEV="_T" OCCUPATION="_T" CUST_BREAKDOWN="_T" COMPOSITE_BREAKDOWN="_L_TRST_NO" DISABILITY_STATUS="_T" ACTIVITY="_T" PRODUCT="_T" UNIT_MEASURE="PT"><Obs TIME_DETAIL="2016" OBS_VALUE="3.7" TIME_PERIOD="2016"/></Series><Series FREQ="A" REPORTING_TYPE="N" SERIES="&#1082; &#1089;&#1083;&#1091;&#1078;&#1073;&#1077; &#1101;&#1082;&#1086;&#1085;&#1086;&#1084;&#1080;&#1095;&#1077;&#1089;&#1082;&#1080;&#1093; &#1088;&#1072;&#1089;&#1089;&#1083;&#1077;&#1076;&#1086;&#1074;&#1072;&#1085;&#1080;&#1081;" REF_AREA="_T" SEX="_T" AGE="_T" URBANISATION="_T" INCOME_WEALTH_QUANTILE="_T" EDUCATION_LEV="_T" OCCUPATION="_T" CUST_BREAKDOWN="_T" COMPOSITE_BREAKDOWN="_L_TRST_NEV" DISABILITY_STATUS="_T" ACTIVITY="_T" PRODUCT="_T" UNIT_MEASURE="PT"><Obs TIME_DETAIL="2016" OBS_VALUE="39.1" TIME_PERIOD="2016"/></Series><Series FREQ="A" REPORTING_TYPE="N" SERIES="&#1082; &#1086;&#1088;&#1075;&#1072;&#1085;&#1072;&#1084; &#1075;&#1088;&#1072;&#1078;&#1076;&#1072;&#1085;&#1089;&#1082;&#1086;&#1081; &#1079;&#1072;&#1097;&#1080;&#1090;&#1099;" REF_AREA="_T" SEX="_T" AGE="_T" URBANISATION="_T" INCOME_WEALTH_QUANTILE="_T" EDUCATION_LEV="_T" OCCUPATION="_T" CUST_BREAKDOWN="_T" COMPOSITE_BREAKDOWN="_L_TRST_HIGH" DISABILITY_STATUS="_T" ACTIVITY="_T" PRODUCT="_T" UNIT_MEASURE="PT"><Obs TIME_DETAIL="2016" OBS_VALUE="20.1" TIME_PERIOD="2016"/></Series><Series FREQ="A" REPORTING_TYPE="N" SERIES="&#1082; &#1086;&#1088;&#1075;&#1072;&#1085;&#1072;&#1084; &#1075;&#1088;&#1072;&#1078;&#1076;&#1072;&#1085;&#1089;&#1082;&#1086;&#1081; &#1079;&#1072;&#1097;&#1080;&#1090;&#1099;" REF_AREA="_T" SEX="_T" AGE="_T" URBANISATION="_T" INCOME_WEALTH_QUANTILE="_T" EDUCATION_LEV="_T" OCCUPATION="_T" CUST_BREAKDOWN="_T" COMPOSITE_BREAKDOWN="_L_TRST_AVG" DISABILITY_STATUS="_T" ACTIVITY="_T" PRODUCT="_T" UNIT_MEASURE="PT"><Obs TIME_DETAIL="2016" OBS_VALUE="40.7" TIME_PERIOD="2016"/></Series><Series FREQ="A" REPORTING_TYPE="N" SERIES="&#1082; &#1086;&#1088;&#1075;&#1072;&#1085;&#1072;&#1084; &#1075;&#1088;&#1072;&#1078;&#1076;&#1072;&#1085;&#1089;&#1082;&#1086;&#1081; &#1079;&#1072;&#1097;&#1080;&#1090;&#1099;" REF_AREA="_T" SEX="_T" AGE="_T" URBANISATION="_T" INCOME_WEALTH_QUANTILE="_T" EDUCATION_LEV="_T" OCCUPATION="_T" CUST_BREAKDOWN="_T" COMPOSITE_BREAKDOWN="_L_TRST_LOW" DISABILITY_STATUS="_T" ACTIVITY="_T" PRODUCT="_T" UNIT_MEASURE="PT"><Obs TIME_DETAIL="2016" OBS_VALUE="4.7" TIME_PERIOD="2016"/></Series><Series FREQ="A" REPORTING_TYPE="N" SERIES="&#1082; &#1086;&#1088;&#1075;&#1072;&#1085;&#1072;&#1084; &#1075;&#1088;&#1072;&#1078;&#1076;&#1072;&#1085;&#1089;&#1082;&#1086;&#1081; &#1079;&#1072;&#1097;&#1080;&#1090;&#1099;" REF_AREA="_T" SEX="_T" AGE="_T" URBANISATION="_T" INCOME_WEALTH_QUANTILE="_T" EDUCATION_LEV="_T" OCCUPATION="_T" CUST_BREAKDOWN="_T" COMPOSITE_BREAKDOWN="_L_TRST_NO" DISABILITY_STATUS="_T" ACTIVITY="_T" PRODUCT="_T" UNIT_MEASURE="PT"><Obs TIME_DETAIL="2016" OBS_VALUE="2.2" TIME_PERIOD="2016"/></Series><Series FREQ="A" REPORTING_TYPE="N" SERIES="&#1082; &#1086;&#1088;&#1075;&#1072;&#1085;&#1072;&#1084; &#1075;&#1088;&#1072;&#1078;&#1076;&#1072;&#1085;&#1089;&#1082;&#1086;&#1081; &#1079;&#1072;&#1097;&#1080;&#1090;&#1099;" REF_AREA="_T" SEX="_T" AGE="_T" URBANISATION="_T" INCOME_WEALTH_QUANTILE="_T" EDUCATION_LEV="_T" OCCUPATION="_T" CUST_BREAKDOWN="_T" COMPOSITE_BREAKDOWN="_L_TRST_NEV" DISABILITY_STATUS="_T" ACTIVITY="_T" PRODUCT="_T" UNIT_MEASURE="PT"><Obs TIME_DETAIL="2016" OBS_VALUE="32.3" TIME_PERIOD="2016"/></Series><Series FREQ="A" REPORTING_TYPE="N" SERIES="&#1086;&#1088;&#1075;&#1072;&#1085;&#1072;&#1084; &#1087;&#1088;&#1086;&#1082;&#1091;&#1088;&#1072;&#1090;&#1091;&#1088;&#1099; &#1084;&#1086;&#1078;&#1085;&#1086; &#1076;&#1086;&#1074;&#1077;&#1088;&#1103;&#1090;&#1100;" REF_AREA="_T" SEX="_T" AGE="_T" URBANISATION="_T" INCOME_WEALTH_QUANTILE="_T" EDUCATION_LEV="_T" OCCUPATION="_T" CUST_BREAKDOWN="_T" COMPOSITE_BREAKDOWN="_L_TRST_STRAGG" DISABILITY_STATUS="_T" ACTIVITY="_T" PRODUCT="_T" UNIT_MEASURE="PT"><Obs TIME_DETAIL="2019" OBS_VALUE="45.9" TIME_PERIOD="2019"/></Series><Series FREQ="A" REPORTING_TYPE="N" SERIES="&#1086;&#1088;&#1075;&#1072;&#1085;&#1072;&#1084; &#1087;&#1088;&#1086;&#1082;&#1091;&#1088;&#1072;&#1090;&#1091;&#1088;&#1099; &#1084;&#1086;&#1078;&#1085;&#1086; &#1076;&#1086;&#1074;&#1077;&#1088;&#1103;&#1090;&#1100;" REF_AREA="_T" SEX="_T" AGE="_T" URBANISATION="_T" INCOME_WEALTH_QUANTILE="_T" EDUCATION_LEV="_T" OCCUPATION="_T" CUST_BREAKDOWN="_T" COMPOSITE_BREAKDOWN="_L_TRST_PARTAGG" DISABILITY_STATUS="_T" ACTIVITY="_T" PRODUCT="_T" UNIT_MEASURE="PT"><Obs TIME_DETAIL="2019" OBS_VALUE="43.4" TIME_PERIOD="2019"/></Series><Series FREQ="A" REPORTING_TYPE="N" SERIES="&#1086;&#1088;&#1075;&#1072;&#1085;&#1072;&#1084; &#1087;&#1088;&#1086;&#1082;&#1091;&#1088;&#1072;&#1090;&#1091;&#1088;&#1099; &#1084;&#1086;&#1078;&#1085;&#1086; &#1076;&#1086;&#1074;&#1077;&#1088;&#1103;&#1090;&#1100;" REF_AREA="_T" SEX="_T" AGE="_T" URBANISATION="_T" INCOME_WEALTH_QUANTILE="_T" EDUCATION_LEV="_T" OCCUPATION="_T" CUST_BREAKDOWN="_T" COMPOSITE_BREAKDOWN="_L_TRST_PARTDIS" DISABILITY_STATUS="_T" ACTIVITY="_T" PRODUCT="_T" UNIT_MEASURE="PT"><Obs TIME_DETAIL="2019" OBS_VALUE="1.6" TIME_PERIOD="2019"/></Series><Series FREQ="A" REPORTING_TYPE="N" SERIES="&#1086;&#1088;&#1075;&#1072;&#1085;&#1072;&#1084; &#1087;&#1088;&#1086;&#1082;&#1091;&#1088;&#1072;&#1090;&#1091;&#1088;&#1099; &#1084;&#1086;&#1078;&#1085;&#1086; &#1076;&#1086;&#1074;&#1077;&#1088;&#1103;&#1090;&#1100;" REF_AREA="_T" SEX="_T" AGE="_T" URBANISATION="_T" INCOME_WEALTH_QUANTILE="_T" EDUCATION_LEV="_T" OCCUPATION="_T" CUST_BREAKDOWN="_T" COMPOSITE_BREAKDOWN="_L_TRST_STRDIS" DISABILITY_STATUS="_T" ACTIVITY="_T" PRODUCT="_T" UNIT_MEASURE="PT"><Obs TIME_DETAIL="2019" OBS_VALUE="1.0" TIME_PERIOD="2019"/></Series><Series FREQ="A" REPORTING_TYPE="N" SERIES="&#1086;&#1088;&#1075;&#1072;&#1085;&#1072;&#1084; &#1087;&#1088;&#1086;&#1082;&#1091;&#1088;&#1072;&#1090;&#1091;&#1088;&#1099; &#1084;&#1086;&#1078;&#1085;&#1086; &#1076;&#1086;&#1074;&#1077;&#1088;&#1103;&#1090;&#1100;" REF_AREA="_T" SEX="_T" AGE="_T" URBANISATION="_T" INCOME_WEALTH_QUANTILE="_T" EDUCATION_LEV="_T" OCCUPATION="_T" CUST_BREAKDOWN="_T" COMPOSITE_BREAKDOWN="_L_TRST_NEV" DISABILITY_STATUS="_T" ACTIVITY="_T" PRODUCT="_T" UNIT_MEASURE="PT"><Obs TIME_DETAIL="2019" OBS_VALUE="8.1" TIME_PERIOD="2019"/></Series><Series FREQ="A" REPORTING_TYPE="N" SERIES="&#1086;&#1088;&#1075;&#1072;&#1085;&#1072;&#1084; &#1087;&#1086;&#1083;&#1080;&#1094;&#1080;&#1080; &#1084;&#1086;&#1078;&#1085;&#1086; &#1076;&#1086;&#1074;&#1077;&#1088;&#1103;&#1090;&#1100;" REF_AREA="_T" SEX="_T" AGE="_T" URBANISATION="_T" INCOME_WEALTH_QUANTILE="_T" EDUCATION_LEV="_T" OCCUPATION="_T" CUST_BREAKDOWN="_T" COMPOSITE_BREAKDOWN="_L_TRST_STRAGG" DISABILITY_STATUS="_T" ACTIVITY="_T" PRODUCT="_T" UNIT_MEASURE="PT"><Obs TIME_DETAIL="2019" OBS_VALUE="38.3" TIME_PERIOD="2019"/></Series><Series FREQ="A" REPORTING_TYPE="N" SERIES="&#1086;&#1088;&#1075;&#1072;&#1085;&#1072;&#1084; &#1087;&#1086;&#1083;&#1080;&#1094;&#1080;&#1080; &#1084;&#1086;&#1078;&#1085;&#1086; &#1076;&#1086;&#1074;&#1077;&#1088;&#1103;&#1090;&#1100;" REF_AREA="_T" SEX="_T" AGE="_T" URBANISATION="_T" INCOME_WEALTH_QUANTILE="_T" EDUCATION_LEV="_T" OCCUPATION="_T" CUST_BREAKDOWN="_T" COMPOSITE_BREAKDOWN="_L_TRST_PARTAGG" DISABILITY_STATUS="_T" ACTIVITY="_T" PRODUCT="_T" UNIT_MEASURE="PT"><Obs TIME_DETAIL="2019" OBS_VALUE="51.2" TIME_PERIOD="2019"/></Series><Series FREQ="A" REPORTING_TYPE="N" SERIES="&#1086;&#1088;&#1075;&#1072;&#1085;&#1072;&#1084; &#1087;&#1086;&#1083;&#1080;&#1094;&#1080;&#1080; &#1084;&#1086;&#1078;&#1085;&#1086; &#1076;&#1086;&#1074;&#1077;&#1088;&#1103;&#1090;&#1100;" REF_AREA="_T" SEX="_T" AGE="_T" URBANISATION="_T" INCOME_WEALTH_QUANTILE="_T" EDUCATION_LEV="_T" OCCUPATION="_T" CUST_BREAKDOWN="_T" COMPOSITE_BREAKDOWN="_L_TRST_PARTDIS" DISABILITY_STATUS="_T" ACTIVITY="_T" PRODUCT="_T" UNIT_MEASURE="PT"><Obs TIME_DETAIL="2019" OBS_VALUE="3.3" TIME_PERIOD="2019"/></Series><Series FREQ="A" REPORTING_TYPE="N" SERIES="&#1086;&#1088;&#1075;&#1072;&#1085;&#1072;&#1084; &#1087;&#1086;&#1083;&#1080;&#1094;&#1080;&#1080; &#1084;&#1086;&#1078;&#1085;&#1086; &#1076;&#1086;&#1074;&#1077;&#1088;&#1103;&#1090;&#1100;" REF_AREA="_T" SEX="_T" AGE="_T" URBANISATION="_T" INCOME_WEALTH_QUANTILE="_T" EDUCATION_LEV="_T" OCCUPATION="_T" CUST_BREAKDOWN="_T" COMPOSITE_BREAKDOWN="_L_TRST_STRDIS" DISABILITY_STATUS="_T" ACTIVITY="_T" PRODUCT="_T" UNIT_MEASURE="PT"><Obs TIME_DETAIL="2019" OBS_VALUE="2.3" TIME_PERIOD="2019"/></Series><Series FREQ="A" REPORTING_TYPE="N" SERIES="&#1086;&#1088;&#1075;&#1072;&#1085;&#1072;&#1084; &#1087;&#1086;&#1083;&#1080;&#1094;&#1080;&#1080; &#1084;&#1086;&#1078;&#1085;&#1086; &#1076;&#1086;&#1074;&#1077;&#1088;&#1103;&#1090;&#1100;" REF_AREA="_T" SEX="_T" AGE="_T" URBANISATION="_T" INCOME_WEALTH_QUANTILE="_T" EDUCATION_LEV="_T" OCCUPATION="_T" CUST_BREAKDOWN="_T" COMPOSITE_BREAKDOWN="_L_TRST_NEV" DISABILITY_STATUS="_T" ACTIVITY="_T" PRODUCT="_T" UNIT_MEASURE="PT"><Obs TIME_DETAIL="2019" OBS_VALUE="4.9" TIME_PERIOD="2019"/></Series><Series FREQ="A" REPORTING_TYPE="N" SERIES="&#1072;&#1085;&#1090;&#1080;&#1082;&#1086;&#1088;&#1088;&#1091;&#1087;&#1094;&#1080;&#1086;&#1085;&#1085;&#1086;&#1081; &#1089;&#1083;&#1091;&#1078;&#1073;&#1077; &#1084;&#1086;&#1078;&#1085;&#1086; &#1076;&#1086;&#1074;&#1077;&#1088;&#1103;&#1090;&#1100;" REF_AREA="_T" SEX="_T" AGE="_T" URBANISATION="_T" INCOME_WEALTH_QUANTILE="_T" EDUCATION_LEV="_T" OCCUPATION="_T" CUST_BREAKDOWN="_T" COMPOSITE_BREAKDOWN="_L_TRST_STRAGG" DISABILITY_STATUS="_T" ACTIVITY="_T" PRODUCT="_T" UNIT_MEASURE="PT"><Obs TIME_DETAIL="2019" OBS_VALUE="25.3" TIME_PERIOD="2019"/></Series><Series FREQ="A" REPORTING_TYPE="N" SERIES="&#1072;&#1085;&#1090;&#1080;&#1082;&#1086;&#1088;&#1088;&#1091;&#1087;&#1094;&#1080;&#1086;&#1085;&#1085;&#1086;&#1081; &#1089;&#1083;&#1091;&#1078;&#1073;&#1077; &#1084;&#1086;&#1078;&#1085;&#1086; &#1076;&#1086;&#1074;&#1077;&#1088;&#1103;&#1090;&#1100;" REF_AREA="_T" SEX="_T" AGE="_T" URBANISATION="_T" INCOME_WEALTH_QUANTILE="_T" EDUCATION_LEV="_T" OCCUPATION="_T" CUST_BREAKDOWN="_T" COMPOSITE_BREAKDOWN="_L_TRST_PARTAGG" DISABILITY_STATUS="_T" ACTIVITY="_T" PRODUCT="_T" UNIT_MEASURE="PT"><Obs TIME_DETAIL="2019" OBS_VALUE="39.9" TIME_PERIOD="2019"/></Series><Series FREQ="A" REPORTING_TYPE="N" SERIES="&#1072;&#1085;&#1090;&#1080;&#1082;&#1086;&#1088;&#1088;&#1091;&#1087;&#1094;&#1080;&#1086;&#1085;&#1085;&#1086;&#1081; &#1089;&#1083;&#1091;&#1078;&#1073;&#1077; &#1084;&#1086;&#1078;&#1085;&#1086; &#1076;&#1086;&#1074;&#1077;&#1088;&#1103;&#1090;&#1100;" REF_AREA="_T" SEX="_T" AGE="_T" URBANISATION="_T" INCOME_WEALTH_QUANTILE="_T" EDUCATION_LEV="_T" OCCUPATION="_T" CUST_BREAKDOWN="_T" COMPOSITE_BREAKDOWN="_L_TRST_PARTDIS" DISABILITY_STATUS="_T" ACTIVITY="_T" PRODUCT="_T" UNIT_MEASURE="PT"><Obs TIME_DETAIL="2019" OBS_VALUE="2.2" TIME_PERIOD="2019"/></Series><Series FREQ="A" REPORTING_TYPE="N" SERIES="&#1072;&#1085;&#1090;&#1080;&#1082;&#1086;&#1088;&#1088;&#1091;&#1087;&#1094;&#1080;&#1086;&#1085;&#1085;&#1086;&#1081; &#1089;&#1083;&#1091;&#1078;&#1073;&#1077; &#1084;&#1086;&#1078;&#1085;&#1086; &#1076;&#1086;&#1074;&#1077;&#1088;&#1103;&#1090;&#1100;" REF_AREA="_T" SEX="_T" AGE="_T" URBANISATION="_T" INCOME_WEALTH_QUANTILE="_T" EDUCATION_LEV="_T" OCCUPATION="_T" CUST_BREAKDOWN="_T" COMPOSITE_BREAKDOWN="_L_TRST_STRDIS" DISABILITY_STATUS="_T" ACTIVITY="_T" PRODUCT="_T" UNIT_MEASURE="PT"><Obs TIME_DETAIL="2019" OBS_VALUE="1.6" TIME_PERIOD="2019"/></Series><Series FREQ="A" REPORTING_TYPE="N" SERIES="&#1072;&#1085;&#1090;&#1080;&#1082;&#1086;&#1088;&#1088;&#1091;&#1087;&#1094;&#1080;&#1086;&#1085;&#1085;&#1086;&#1081; &#1089;&#1083;&#1091;&#1078;&#1073;&#1077; &#1084;&#1086;&#1078;&#1085;&#1086; &#1076;&#1086;&#1074;&#1077;&#1088;&#1103;&#1090;&#1100;" REF_AREA="_T" SEX="_T" AGE="_T" URBANISATION="_T" INCOME_WEALTH_QUANTILE="_T" EDUCATION_LEV="_T" OCCUPATION="_T" CUST_BREAKDOWN="_T" COMPOSITE_BREAKDOWN="_L_TRST_NEV" DISABILITY_STATUS="_T" ACTIVITY="_T" PRODUCT="_T" UNIT_MEASURE="PT"><Obs TIME_DETAIL="2019" OBS_VALUE="31.0" TIME_PERIOD="2019"/></Series><Series FREQ="A" REPORTING_TYPE="N" SERIES="&#1089;&#1083;&#1091;&#1078;&#1073;&#1077; &#1101;&#1082;&#1086;&#1085;&#1086;&#1084;&#1080;&#1095;&#1077;&#1089;&#1082;&#1080;&#1093; &#1088;&#1072;&#1089;&#1089;&#1083;&#1077;&#1076;&#1086;&#1074;&#1072;&#1085;&#1080;&#1081; &#1084;&#1086;&#1078;&#1085;&#1086; &#1076;&#1086;&#1074;&#1077;&#1088;&#1103;&#1090;&#1100;" REF_AREA="_T" SEX="_T" AGE="_T" URBANISATION="_T" INCOME_WEALTH_QUANTILE="_T" EDUCATION_LEV="_T" OCCUPATION="_T" CUST_BREAKDOWN="_T" COMPOSITE_BREAKDOWN="_L_TRST_STRAGG" DISABILITY_STATUS="_T" ACTIVITY="_T" PRODUCT="_T" UNIT_MEASURE="PT"><Obs TIME_DETAIL="2019" OBS_VALUE="24.4" TIME_PERIOD="2019"/></Series><Series FREQ="A" REPORTING_TYPE="N" SERIES="&#1089;&#1083;&#1091;&#1078;&#1073;&#1077; &#1101;&#1082;&#1086;&#1085;&#1086;&#1084;&#1080;&#1095;&#1077;&#1089;&#1082;&#1080;&#1093; &#1088;&#1072;&#1089;&#1089;&#1083;&#1077;&#1076;&#1086;&#1074;&#1072;&#1085;&#1080;&#1081; &#1084;&#1086;&#1078;&#1085;&#1086; &#1076;&#1086;&#1074;&#1077;&#1088;&#1103;&#1090;&#1100;" REF_AREA="_T" SEX="_T" AGE="_T" URBANISATION="_T" INCOME_WEALTH_QUANTILE="_T" EDUCATION_LEV="_T" OCCUPATION="_T" CUST_BREAKDOWN="_T" COMPOSITE_BREAKDOWN="_L_TRST_PARTAGG" DISABILITY_STATUS="_T" ACTIVITY="_T" PRODUCT="_T" UNIT_MEASURE="PT"><Obs TIME_DETAIL="2019" OBS_VALUE="35.7" TIME_PERIOD="2019"/></Series><Series FREQ="A" REPORTING_TYPE="N" SERIES="&#1089;&#1083;&#1091;&#1078;&#1073;&#1077; &#1101;&#1082;&#1086;&#1085;&#1086;&#1084;&#1080;&#1095;&#1077;&#1089;&#1082;&#1080;&#1093; &#1088;&#1072;&#1089;&#1089;&#1083;&#1077;&#1076;&#1086;&#1074;&#1072;&#1085;&#1080;&#1081; &#1084;&#1086;&#1078;&#1085;&#1086; &#1076;&#1086;&#1074;&#1077;&#1088;&#1103;&#1090;&#1100;" REF_AREA="_T" SEX="_T" AGE="_T" URBANISATION="_T" INCOME_WEALTH_QUANTILE="_T" EDUCATION_LEV="_T" OCCUPATION="_T" CUST_BREAKDOWN="_T" COMPOSITE_BREAKDOWN="_L_TRST_PARTDIS" DISABILITY_STATUS="_T" ACTIVITY="_T" PRODUCT="_T" UNIT_MEASURE="PT"><Obs TIME_DETAIL="2019" OBS_VALUE="1.6" TIME_PERIOD="2019"/></Series><Series FREQ="A" REPORTING_TYPE="N" SERIES="&#1089;&#1083;&#1091;&#1078;&#1073;&#1077; &#1101;&#1082;&#1086;&#1085;&#1086;&#1084;&#1080;&#1095;&#1077;&#1089;&#1082;&#1080;&#1093; &#1088;&#1072;&#1089;&#1089;&#1083;&#1077;&#1076;&#1086;&#1074;&#1072;&#1085;&#1080;&#1081; &#1084;&#1086;&#1078;&#1085;&#1086; &#1076;&#1086;&#1074;&#1077;&#1088;&#1103;&#1090;&#1100;" REF_AREA="_T" SEX="_T" AGE="_T" URBANISATION="_T" INCOME_WEALTH_QUANTILE="_T" EDUCATION_LEV="_T" OCCUPATION="_T" CUST_BREAKDOWN="_T" COMPOSITE_BREAKDOWN="_L_TRST_STRDIS" DISABILITY_STATUS="_T" ACTIVITY="_T" PRODUCT="_T" UNIT_MEASURE="PT"><Obs TIME_DETAIL="2019" OBS_VALUE="1.2" TIME_PERIOD="2019"/></Series><Series FREQ="A" REPORTING_TYPE="N" SERIES="&#1089;&#1083;&#1091;&#1078;&#1073;&#1077; &#1101;&#1082;&#1086;&#1085;&#1086;&#1084;&#1080;&#1095;&#1077;&#1089;&#1082;&#1080;&#1093; &#1088;&#1072;&#1089;&#1089;&#1083;&#1077;&#1076;&#1086;&#1074;&#1072;&#1085;&#1080;&#1081; &#1084;&#1086;&#1078;&#1085;&#1086; &#1076;&#1086;&#1074;&#1077;&#1088;&#1103;&#1090;&#1100;" REF_AREA="_T" SEX="_T" AGE="_T" URBANISATION="_T" INCOME_WEALTH_QUANTILE="_T" EDUCATION_LEV="_T" OCCUPATION="_T" CUST_BREAKDOWN="_T" COMPOSITE_BREAKDOWN="_L_TRST_NEV" DISABILITY_STATUS="_T" ACTIVITY="_T" PRODUCT="_T" UNIT_MEASURE="PT"><Obs TIME_DETAIL="2019" OBS_VALUE="37.1" TIME_PERIOD="2019"/></Series></mes:DataSet></mes:StructureSpecificData>