{
  "resources": [
    {
      "path": "data.csv",
      "name": "data",
      "profile": "tabular-data-resource",
      "scheme": "file",
      "format": "csv",
      "hashing": "md5",
      "encoding": "utf-8",
      "schema": {
        "fields": [
          {
            "name": "COMPOSITE_BREAKDOWN",
            "type": "string",
            "constraints": {
              "enum": [
                "",
                "Донор ретінде Қазақстан бойынша деректер",
                "Алушы ретінде Қазақстан бойынша деректер"
              ]
            },
            "title": "COMPOSITE_BREAKDOWN"
          },
          {
            "name": "UNIT_MEASURE",
            "type": "string",
            "title": "UNIT_MEASURE"
          },
          {
            "name": "Value",
            "type": "number",
            "title": "Value"
          },
          {
            "name": "Year",
            "type": "integer",
            "title": "Year"
          }
        ]
      }
    }
  ],
  "profile": "data-package",
  "name": "17-19-1",
  "title": "Статистика саласындағы дамушы елдердің әлеуетін арттыруға бөлінген барлық ресурстардың құны (АҚШ долларымен))"
}