{"data":{"Year":[2010,2010,2010,2010,2010,2010,2010,2010,2010,2010,2010,2010,2010,2010,2010,2010,2011,2011,2011,2011,2011,2011,2011,2011,2011,2011,2011,2011,2011,2011,2011,2012,2012,2012,2012,2012,2012,2012,2012,2012,2012,2012,2012,2012,2013,2013,2013,2013,2013,2013,2013,2013,2013,2013,2013,2013,2013,2013,2013,2013,2013,2014,2014,2014,2014,2014,2014,2014,2014,2014,2014,2014,2014,2014,2014,2014,2014,2014,2015,2015,2015,2015,2015,2015,2015,2015,2015,2015,2015,2015,2015,2015,2015,2015,2015,2016,2016,2016,2016,2016,2016,2016,2016,2016,2016,2016,2016,2016,2016,2016,2016,2016,2017,2017,2017,2017,2017,2017,2017,2017,2017,2017,2017,2017,2017,2017,2017,2017,2017,2018,2018,2018,2018,2018,2018,2018,2018,2018,2018,2018,2018,2018,2018,2018,2018,2018,2018,2019,2019,2019,2019,2019,2019,2019,2019,2019,2019,2019,2019,2019,2019,2019,2019,2019,2019,2020,2020,2020,2020,2020,2020,2020,2020,2020,2020,2020,2020,2020,2020,2020,2020,2020,2020],"Regions":[null,"Aktobe","Almaty","Atyrau","Batys Kazakhstan","Zhambyl","Karagandy","Kostanay","Kyzylorda","Mangistau","Ontustik Kazakhstan","Pavlodar","Soltustik Kazakhstan","Shygys Kazakhstan","Nur-Sultan city","Almaty city",null,"Akmola","Aktobe","Almaty","Atyrau","Zhambyl","Karagandy","Kostanay","Kyzylorda","Mangistau","Ontustik Kazakhstan","Pavlodar","Shygys Kazakhstan","Nur-Sultan city","Almaty city",null,"Akmola","Almaty","Atyrau","Zhambyl","Karagandy","Kyzylorda","Mangistau","Ontustik Kazakhstan","Pavlodar","Soltustik Kazakhstan","Shygys Kazakhstan","Almaty city",null,"Akmola","Aktobe","Almaty","Atyrau","Batys Kazakhstan","Zhambyl","Karagandy","Kostanay","Kyzylorda","Mangistau","Ontustik Kazakhstan","Pavlodar","Soltustik Kazakhstan","Shygys Kazakhstan","Nur-Sultan city","Almaty city",null,"Akmola","Aktobe","Almaty","Atyrau","Batys Kazakhstan","Zhambyl","Karagandy","Kostanay","Kyzylorda","Mangistau","Ontustik Kazakhstan","Pavlodar","Soltustik Kazakhstan","Shygys Kazakhstan","Nur-Sultan city","Almaty city",null,"Akmola","Aktobe","Almaty","Atyrau","Batys Kazakhstan","Zhambyl","Karagandy","Kostanay","Kyzylorda","Mangistau","Ontustik Kazakhstan","Pavlodar","Soltustik Kazakhstan","Shygys Kazakhstan","Nur-Sultan city","Almaty city",null,"Akmola","Aktobe","Almaty","Atyrau","Batys Kazakhstan","Zhambyl","Karagandy","Kostanay","Kyzylorda","Mangistau","Ontustik Kazakhstan","Pavlodar","Soltustik Kazakhstan","Shygys Kazakhstan","Nur-Sultan city","Almaty city",null,"Akmola","Aktobe","Almaty","Atyrau","Batys Kazakhstan","Zhambyl","Karagandy","Kostanay","Kyzylorda","Mangistau","Ontustik Kazakhstan","Pavlodar","Soltustik Kazakhstan","Shygys Kazakhstan","Nur-Sultan city","Almaty city",null,"Akmola","Aktobe","Almaty","Atyrau","Batys Kazakhstan","Zhambyl","Karagandy","Kostanay","Kyzylorda","Mangistau","Pavlodar","Soltustik Kazakhstan","Turkistan","Shygys Kazakhstan","Nur-Sultan city","Almaty city","Shymkent city",null,"Akmola","Aktobe","Almaty","Atyrau","Batys Kazakhstan","Zhambyl","Karagandy","Kostanay","Kyzylorda","Mangistau","Pavlodar","Soltustik Kazakhstan","Turkistan","Shygys Kazakhstan","Nur-Sultan city","Almaty city","Shymkent city",null,"Akmola","Aktobe","Almaty","Atyrau","Batys Kazakhstan","Zhambyl","Karagandy","Kostanay","Kyzylorda","Mangistau","Pavlodar","Soltustik Kazakhstan","Turkistan","Shygys Kazakhstan","Nur-Sultan city","Almaty city","Shymkent city"],"GeoCode":[null,"KZAKT","KZALM","KZATY","KZZAP","KZZHA","KZKAR","KZKUS","KZKZY","KZMAN","KZONT","KZPAV","KZSEV","KZVOS","KZNS","KZALA",null,"KZAKM","KZAKT","KZALM","KZATY","KZZHA","KZKAR","KZKUS","KZKZY","KZMAN","KZONT","KZPAV","KZVOS","KZNS","KZALA",null,"KZAKM","KZALM","KZATY","KZZHA","KZKAR","KZKZY","KZMAN","KZONT","KZPAV","KZSEV","KZVOS","KZALA",null,"KZAKM","KZAKT","KZALM","KZATY","KZZAP","KZZHA","KZKAR","KZKUS","KZKZY","KZMAN","KZONT","KZPAV","KZSEV","KZVOS","KZNS","KZALA",null,"KZAKM","KZAKT","KZALM","KZATY","KZZAP","KZZHA","KZKAR","KZKUS","KZKZY","KZMAN","KZONT","KZPAV","KZSEV","KZVOS","KZNS","KZALA",null,"KZAKM","KZAKT","KZALM","KZATY","KZZAP","KZZHA","KZKAR","KZKUS","KZKZY","KZMAN","KZONT","KZPAV","KZSEV","KZVOS","KZNS","KZALA",null,"KZAKM","KZAKT","KZALM","KZATY","KZZAP","KZZHA","KZKAR","KZKUS","KZKZY","KZMAN","KZONT","KZPAV","KZSEV","KZVOS","KZNS","KZALA",null,"KZAKM","KZAKT","KZALM","KZATY","KZZAP","KZZHA","KZKAR","KZKUS","KZKZY","KZMAN","KZONT","KZPAV","KZSEV","KZVOS","KZNS","KZALA",null,"KZAKM","KZAKT","KZALM","KZATY","KZZAP","KZZHA","KZKAR","KZKUS","KZKZY","KZMAN","KZPAV","KZSEV","KZYUZ","KZVOS","KZNS","KZALA","KZSHY",null,"KZAKM","KZAKT","KZALM","KZATY","KZZAP","KZZHA","KZKAR","KZKUS","KZKZY","KZMAN","KZPAV","KZSEV","KZYUZ","KZVOS","KZNS","KZALA","KZSHY",null,"KZAKM","KZAKT","KZALM","KZATY","KZZAP","KZZHA","KZKAR","KZKUS","KZKZY","KZMAN","KZPAV","KZSEV","KZYUZ","KZVOS","KZNS","KZALA","KZSHY"],"Value":[22.7,34.5,16.1,20.4,8.3,29.4,4.2,15.4,35.0,6.5,26.7,16.3,24.0,21.5,27.6,6.0,17.4,23.3,16.9,18.9,6.6,22.5,8.2,15.7,10.4,24.7,16.8,7.8,22.4,10.4,15.5,13.5,8.2,7.9,6.4,18.7,16.2,15.0,5.9,20.6,15.5,12.2,13.2,13.0,13.1,25.4,21.3,5.1,25.3,7.9,14.8,4.1,15.3,10.6,11.0,10.2,15.4,12.5,8.9,17.7,10.2,15.20931508,16.93910392,10.10560356,14.49275362,12.29558588,23.09646624,18.11331691,16.06554743,15.73069058,10.01201442,26.55478252,15.4870683,0.0,17.69173417,25.83200586,16.33519827,4.805035677,16.54969045,25.89331952,15.02178158,17.17749258,36.76245328,38.58024691,3.7811472,32.72519022,0.0,48.76198732,5.236424569,15.64822784,13.05994515,15.16587678,22.25189141,7.659900421,2.376651773,15.41663455,0.0,20.19386107,14.47212909,30.14045452,22.77904328,11.53313855,29.3735051,32.72519022,5.335325188,5.052801779,15.98976655,0.0,18.94058968,17.75568182,11.0200933,7.939343416,14.81220423,17.809439,5.25210084,25.08591927,18.40490798,7.764577995,12.22593528,13.22634688,17.08233686,0.0,10.29813089,16.79825298,28.49814762,18.33588726,18.36884644,6.503219093,14.72970982,14.0,35.9,5.1,14.8,5.9,7.6,8.0,26.2,8.7,10.7,25.1,8.5,14.8,10.3,14.0,29.0,8.9,19.6,13.7,17.2,4.9,25.4,17.8,7.6,11.8,39.5,26.6,5.3,4.9,0.0,0.0,9.3,23.4,3.3,15.4,7.1,36.5,25.5,70.3,30.4,50.6,21.9,28.9,51.5,94.4,56.0,36.8,25.7,76.7,16.3,45.0,19.2,23.0,53.3]},"edges":[]}